{
  "source": "built-in open vocabulary",
  "items": [
    {"display": "hello", "target": "hello"},
    {"display": "thanks", "target": "thanks"},
    {"display": "music", "target": "music"},
    {"display": "friend", "target": "friend"},
    {"display": "pixel", "target": "pixel"},
    {"display": "rhythm", "target": "rhythm"},
    {"display": "memory", "target": "memory"},
    {"display": "schedule", "target": "schedule"},
    {"display": "companion", "target": "companion"},
    {"display": "happy", "target": "happy"},
    {"display": "sleep", "target": "sleep"},
    {"display": "work", "target": "work"},
    {"display": "star", "target": "star"},
    {"display": "catch", "target": "catch"},
    {"display": "typing", "target": "typing"},
    {"display": "practice", "target": "practice"}
  ]
}
